clock_timer/__init__.py
clock_timer/__main__.py
clock_timer/base.py
clock_timer/cli.py
clock_timer/entities/__init__.py
clock_timer/entities/clock_logger.py
python_clock_timer-0.4.0.dist-info/LICENSE
python_clock_timer-0.4.0.dist-info/METADATA
python_clock_timer-0.4.0.dist-info/WHEEL
python_clock_timer-0.4.0.dist-info/entry_points.txt
python_clock_timer-0.4.0.dist-info/top_level.txt
python_clock_timer-0.4.0.dist-info/RECORD
